mdr/__init__.py
mdr/_version.py
mdr/continuous_mdr.py
mdr/mdr.py
mdr/mdr_ensemble.py
mdr/utils/__init__.py
mdr/utils/utils.py
scikit_mdr-0.4.6.dist-info/licenses/LICENSE
scikit_mdr-0.4.6.dist-info/METADATA
scikit_mdr-0.4.6.dist-info/WHEEL
scikit_mdr-0.4.6.dist-info/top_level.txt
scikit_mdr-0.4.6.dist-info/zip-safe
scikit_mdr-0.4.6.dist-info/RECORD
